dcors
