Metadata-Version: 1.1
Name: django-dcors
Version: 0.1
Summary: Django middleware for adding CORS HTTP headers.
Home-page: http://github.com/prasanthn/django-dcors
Author: Prasanth Nair
Author-email: prasanth.n@outlook.com
License: MIT
Keywords: django,CORS
Platform: UNKNOWN
Classifier: Development Status :: 5 - Production/Stable
Classifier: Environment :: Web Environment
Classifier: Framework :: Django
Classifier: License :: OSI Approved :: MIT License
Classifier: Operating System :: OS Independent
Classifier: Operating System :: OS Independent
Classifier: Programming Language :: Python :: 2.7
Classifier: Topic :: Internet :: WWW/HTTP
Classifier: Topic :: Internet :: WWW/HTTP :: Dynamic Content
Classifier: Topic :: Software Development :: Libraries :: Python Modules
